netunicorn/client/__init__.py
netunicorn/client/base.py
netunicorn/client/remote.py
netunicorn_client-0.4.0.dist-info/METADATA
netunicorn_client-0.4.0.dist-info/WHEEL
netunicorn_client-0.4.0.dist-info/top_level.txt
netunicorn_client-0.4.0.dist-info/RECORD
