Metadata-Version: 2.1
Name: netunicorn-client
Version: 0.4.0
Summary: netunicorn client module
Author-email: Roman Beltiukov <rbeltiukov@ucsb.edu>
License: MIT
Keywords: netunicorn
Classifier: Programming Language :: Python :: 3
Classifier: Programming Language :: Python :: 3.8
Classifier: Programming Language :: Python :: 3.9
Classifier: Programming Language :: Python :: 3.10
Classifier: Programming Language :: Python :: 3.11
Classifier: Programming Language :: Python :: 3.12
Requires-Python: >=3.8
Requires-Dist: netunicorn-base <0.5.0,>=0.4.0
Requires-Dist: cloudpickle
Requires-Dist: requests
Requires-Dist: returns
